README.md
mtg_ontology/__init__.py
mtg_ontology/datamodel/__init__.py
mtg_ontology/datamodel/mtg_ontology.py
mtg_ontology/helpers.py
mtg_ontology/schema/abilities.yaml
mtg_ontology/schema/cards.yaml
mtg_ontology/schema/mtg_ontology.yaml
mtg_ontology-0.3.3.dist-info/LICENSE
mtg_ontology-0.3.3.dist-info/METADATA
mtg_ontology-0.3.3.dist-info/WHEEL
mtg_ontology-0.3.3.dist-info/RECORD
