Metadata-Version: 2.1
Name: mtg-ontology
Version: 0.3.3
Summary: An ontology describing Magic: The Gathering.
License: GNU GPL v3.0
Author: Cyril Matthey-Doret
Author-email: cmdoret@mailbox.org
Requires-Python: >=3.9,<3.12
Classifier: License :: Other/Proprietary License
Classifier: Programming Language :: Python :: 3
Classifier: Programming Language :: Python :: 3.9
Classifier: Programming Language :: Python :: 3.10
Classifier: Programming Language :: Python :: 3.11
Provides-Extra: docs
Requires-Dist: linkml-runtime (>=1.1.24,<2.0.0)
